sctools/__init__.py
sctools/bam.py
sctools/barcode.py
sctools/encodings.py
sctools/fastq.py
sctools/gtf.py
sctools/platform.py
sctools/reader.py
sctools/stats.py
sctools/test/__init__.py
sctools/test/test_bam.py
sctools/test/test_barcode.py
sctools/test/test_encodings.py
sctools/test/test_entrypoints.py
sctools/test/test_fastq.py
sctools/test/test_gtf.py
sctools/test/test_stats.py
sctools/test/data/1k-august-2016.txt
sctools/test/data/test.bam
sctools/test/data/test.gtf
sctools/test/data/test.gtf.bz2
sctools/test/data/test.gtf.gz
sctools/test/data/test.sam
sctools/test/data/test_i7.fastq
sctools/test/data/test_i7.fastq.bz2
sctools/test/data/test_i7.fastq.gz
sctools/test/data/test_r1.fastq
sctools/test/data/test_r1.fastq.bz2
sctools/test/data/test_r1.fastq.gz
sctools/test/data/test_r2.bam
sctools/test/data/test_r2.fastq
sctools/test/data/test_r2.fastq.bz2
sctools/test/data/test_r2.fastq.gz
sctools/test/data/test_r2_tagged.bam
sctools-0.1.6.dist-info/DESCRIPTION.rst
sctools-0.1.6.dist-info/METADATA
sctools-0.1.6.dist-info/RECORD
sctools-0.1.6.dist-info/WHEEL
sctools-0.1.6.dist-info/entry_points.txt
sctools-0.1.6.dist-info/metadata.json
sctools-0.1.6.dist-info/top_level.txt
